setup.py
icu_ea_api/__init__.py
icu_ea_api/icu_ea_api.py
icu_ea_api.egg-info/PKG-INFO
icu_ea_api.egg-info/SOURCES.txt
icu_ea_api.egg-info/dependency_links.txt
icu_ea_api.egg-info/not-zip-safe
icu_ea_api.egg-info/requires.txt
icu_ea_api.egg-info/top_level.txt