Metadata-Version: 1.0
Name: icu-ea-api
Version: 0.4
Summary: A Python API for Imperial College Union's eActivities
Home-page: https://github.com/JCGrant/icu-ea-api
Author: JCGrant
Author-email: jamescolin.grant@gmail.com
License: MIT
Platform: UNKNOWN
